chemperium/__about__.py
chemperium/__init__.py
chemperium/inp.py
chemperium/data/__init__.py
chemperium/data/load_data.py
chemperium/data/load_test_data.py
chemperium/data/parse_csv.py
chemperium/features/__init__.py
chemperium/features/calc_features.py
chemperium/features/featurize.py
chemperium/model/__init__.py
chemperium/model/mpnn.py
chemperium/molecule/__init__.py
chemperium/molecule/batch.py
chemperium/molecule/graph.py
chemperium/postprocessing/__init__.py
chemperium/postprocessing/thermodynamics.py
chemperium/postprocessing/uncertainty_quantification.py
chemperium/training/__init__.py
chemperium/training/evaluate.py
chemperium/training/predict.py
chemperium/training/represent.py
chemperium/training/run.py
chemperium/training/test.py
chemperium/training/train.py
chemperium-0.0.1.dist-info/METADATA
chemperium-0.0.1.dist-info/WHEEL
chemperium-0.0.1.dist-info/licenses/LICENSE
chemperium-0.0.1.dist-info/RECORD
