Metadata-Version: 2.3
Name: chemperium
Version: 0.0.1
Summary: Chemperium package
Project-URL: source, https://github.com/mrodobbe/chemperium
Project-URL: tracker, https://github.com/mrodobbe/chemperium/issues
Author-email: "Maarten R. Dobbelaere" <mrodobbe.dobbelaere@ugent.be>
License: MIT License
License-File: LICENSE
Classifier: Development Status :: 3 - Alpha
Classifier: Intended Audience :: Developers
Classifier: License :: OSI Approved :: MIT License
Classifier: Operating System :: OS Independent
Classifier: Programming Language :: Python
Classifier: Programming Language :: Python :: 3
Classifier: Programming Language :: Python :: 3.8
Classifier: Programming Language :: Python :: 3.9
Classifier: Programming Language :: Python :: 3.10
Classifier: Programming Language :: Python :: 3.11
Classifier: Topic :: Software Development :: Build Tools
Requires-Python: >=3.8
Requires-Dist: keras<3.0
Requires-Dist: numpy
Requires-Dist: pandas
Requires-Dist: rdkit
Requires-Dist: scikit-learn
Requires-Dist: scipy
Requires-Dist: tensorflow<=2.15
Requires-Dist: tqdm
Provides-Extra: test
Requires-Dist: genbadge[coverage]; extra == 'test'
Requires-Dist: hypothesis; extra == 'test'
Requires-Dist: mypy; extra == 'test'
Requires-Dist: pytest; extra == 'test'
Requires-Dist: pytest-cov; extra == 'test'
Requires-Dist: tox; extra == 'test'
